wasabit/__init__.py
wasabit/wasabi_auth.py
wasabit/wasabi_download.py
wasabit/wasabi_upload.py
wasabit-0.2.1.dist-info/LICENSE
wasabit-0.2.1.dist-info/METADATA
wasabit-0.2.1.dist-info/WHEEL
wasabit-0.2.1.dist-info/top_level.txt
wasabit-0.2.1.dist-info/RECORD
